vimnote/__init__.py
vimnote/bookpreview.py
vimnote/bookview.py
vimnote/config.py
vimnote/deletedialog.py
vimnote/exceptions.py
vimnote/notepreview.py
vimnote/noteview.py
vimnote/preview.py
vimnote/tableview.py
vimnote/textbox.py
vimnote-1.0.7.data/data/share/bash-completion/completions/vimnote
vimnote-1.0.7.dist-info/METADATA
vimnote-1.0.7.dist-info/WHEEL
vimnote-1.0.7.dist-info/entry_points.txt
vimnote-1.0.7.dist-info/RECORD
