Metadata-Version: 2.1
Name: vimnote
Version: 1.0.7
Summary: a vim-based TUI notetaking application
License: GPLv3
Author: maxcutlyp
Author-email: max@maxcutlyp.com
Requires-Python: >=3.10
Classifier: License :: Other/Proprietary License
Classifier: Programming Language :: Python :: 3
Classifier: Programming Language :: Python :: 3.10
Classifier: Programming Language :: Python :: 3.11
